caplibproto/__init__.py
caplibproto/analytics.py
caplibproto/dqanalytics_pb2.py
caplibproto/dqanalyticsservice_pb2.py
caplibproto/dqcmanalytics_pb2.py
caplibproto/dqcmanalyticsservice_pb2.py
caplibproto/dqcmmarket_pb2.py
caplibproto/dqcmmarketservice_pb2.py
caplibproto/dqcranalytics_pb2.py
caplibproto/dqcranalyticsservice_pb2.py
caplibproto/dqcrmarket_pb2.py
caplibproto/dqcrmarketservice_pb2.py
caplibproto/dqdatetime_pb2.py
caplibproto/dqdatetimeservice_pb2.py
caplibproto/dqeqanalytics_pb2.py
caplibproto/dqeqanalyticsservice_pb2.py
caplibproto/dqeqmarketservice_pb2.py
caplibproto/dqfianalytics_pb2.py
caplibproto/dqfianalyticsservice_pb2.py
caplibproto/dqfimarket_pb2.py
caplibproto/dqfimarketservice_pb2.py
caplibproto/dqfxanalytics_pb2.py
caplibproto/dqfxanalyticsservice_pb2.py
caplibproto/dqfxmarket_pb2.py
caplibproto/dqfxmarketservice_pb2.py
caplibproto/dqiranalytics_pb2.py
caplibproto/dqiranalyticsservice_pb2.py
caplibproto/dqirmarket_pb2.py
caplibproto/dqirmarketservice_pb2.py
caplibproto/dqlib_pb2.py
caplibproto/dqlib_pb2_grpc.py
caplibproto/dqmarket_pb2.py
caplibproto/dqmarketrisk_pb2.py
caplibproto/dqmarketriskservice_pb2.py
caplibproto/dqmarketservice_pb2.py
caplibproto/dqnumerics_pb2.py
caplibproto/dqproto.py
caplibproto/dqstaticdataservice_pb2.py
caplibproto-0.0.7.dist-info/METADATA
caplibproto-0.0.7.dist-info/WHEEL
caplibproto-0.0.7.dist-info/top_level.txt
caplibproto-0.0.7.dist-info/RECORD
