Metadata-Version: 2.1
Name: caplibproto
Version: 0.0.7
Home-page: 
Author: caprisktech.com
Requires-Python: >= 3.8.0
Requires-Dist: python-dotenv>=0.21.0
Requires-Dist: protobuf==3.20.0
Requires-Dist: grpcio>=1.56.2
